qcrash/__init__.py
qcrash/_hooks.py
qcrash/api.py
qcrash/qt.py
qcrash/_dialogs/__init__.py
qcrash/_dialogs/gh_login.py
qcrash/_dialogs/report.py
qcrash/_dialogs/review.py
qcrash/_extlibs/__init__.py
qcrash/_extlibs/github.py
qcrash/_forms/__init__.py
qcrash/_forms/dlg_github_login_ui.py
qcrash/_forms/dlg_report_bug_ui.py
qcrash/_forms/dlg_review_ui.py
qcrash/_forms/qcrash_rc.py
qcrash/backends/__init__.py
qcrash/backends/base.py
qcrash/backends/email.py
qcrash/backends/github.py
qcrash/formatters/__init__.py
qcrash/formatters/base.py
qcrash/formatters/email.py
qcrash/formatters/markdown.py
qcrash-0.2.0.dist-info/DESCRIPTION.rst
qcrash-0.2.0.dist-info/METADATA
qcrash-0.2.0.dist-info/RECORD
qcrash-0.2.0.dist-info/WHEEL
qcrash-0.2.0.dist-info/entry_points.txt
qcrash-0.2.0.dist-info/metadata.json
qcrash-0.2.0.dist-info/top_level.txt
tests/__init__.py
tests/test_api.py
tests/test_backends/__init__.py
tests/test_backends/test_base.py
tests/test_backends/test_email.py
tests/test_backends/test_github.py
tests/test_dialogs/__init__.py
tests/test_dialogs/test_dlg_report.py
tests/test_dialogs/test_gh_login.py
tests/test_dialogs/test_review.py
tests/test_formatters/__init__.py
tests/test_formatters/test_base.py
tests/test_formatters/test_email.py
tests/test_formatters/test_markdown.py
