Metadata-Version: 2.0
Name: qcrash
Version: 0.2.0
Summary: A crash report framework for PyQt/PySide applications
Home-page: https://github.com/ColinDuquesnoy/qcrash
Author: Colin Duquesnoy
Author-email: colin.duquesnoy@gmail.com
License: MIT
Keywords: Github,PyQt4,PyQt5,PySide,Issue,Report,Crash,Tool
Platform: UNKNOWN
Classifier: Development Status :: 5 - Production/Stable
Classifier: Environment :: X11 Applications :: Qt
Classifier: Environment :: Win32 (MS Windows)
Classifier: Intended Audience :: Developers
Classifier: License :: OSI Approved :: GNU General Public License v3 or later (GPLv3+)
Classifier: Operating System :: Microsoft :: Windows
Classifier: Operating System :: POSIX :: Linux
Classifier: Programming Language :: Python :: 2.7
Classifier: Programming Language :: Python :: 3.2
Classifier: Programming Language :: Python :: 3.3
Classifier: Programming Language :: Python :: 3.4
Classifier: Programming Language :: Python :: 3.5
Classifier: Topic :: Software Development :: Bug Tracking
Classifier: Topic :: Software Development :: User Interfaces
Classifier: Topic :: Software Development :: Widget Sets
Requires-Dist: keyring
